terminaltype/__init__.py
terminaltype/__main__.py
terminaltype/app.py
terminaltype/arguments.py
terminaltype/colors.py
terminaltype/history.py
terminaltype/keys.py
terminaltype/text.py
terminaltype/timer.py
terminaltype/utils.py
terminaltype/window.py
prueba_nashe-0.0.1.dist-info/LICENSE
prueba_nashe-0.0.1.dist-info/METADATA
prueba_nashe-0.0.1.dist-info/WHEEL
prueba_nashe-0.0.1.dist-info/entry_points.txt
prueba_nashe-0.0.1.dist-info/top_level.txt
prueba_nashe-0.0.1.dist-info/RECORD
