Metadata-Version: 2.1
Name: prueba-nashe
Version: 0.0.1
Summary: A simple terminal-based typing test
Home-page: https://github.com/ramirocabral/terminaltype
Author: Ramiro Cabral
Author-email: <ramiro.cabral@alu.ing.unlp.edu.ar>
License: GPL
Keywords: python,typing,test,game,curses
Classifier: Development Status :: 1 - Planning
Classifier: Intended Audience :: Developers
Classifier: Programming Language :: Python :: 3
Classifier: Operating System :: OS Independent
Classifier: License :: OSI Approved :: GNU General Public License v3 (GPLv3)
Requires-Python: >=3.10
License-File: LICENSE
Provides-Extra: dev
Requires-Dist: twine >=4.0.2 ; extra == 'dev'
